odoo/addons/sale_order_cancel_optional_email/README.rst
odoo/addons/sale_order_cancel_optional_email/__init__.py
odoo/addons/sale_order_cancel_optional_email/__manifest__.py
odoo/addons/sale_order_cancel_optional_email/i18n/sale_order_cancel_optional_email.pot
odoo/addons/sale_order_cancel_optional_email/readme/CONTRIBUTORS.md
odoo/addons/sale_order_cancel_optional_email/readme/DESCRIPTION.md
odoo/addons/sale_order_cancel_optional_email/static/description/icon.png
odoo/addons/sale_order_cancel_optional_email/static/description/index.html
odoo/addons/sale_order_cancel_optional_email/tests/__init__.py
odoo/addons/sale_order_cancel_optional_email/tests/test_sale_order_cancel_no_email.py
odoo/addons/sale_order_cancel_optional_email/views/sale_order_views.xml
odoo/addons/sale_order_cancel_optional_email/wizard/sale_order_cancel_views.xml
odoo_addon_sale_order_cancel_optional_email-18.0.1.0.0.2.dist-info/METADATA
odoo_addon_sale_order_cancel_optional_email-18.0.1.0.0.2.dist-info/WHEEL
odoo_addon_sale_order_cancel_optional_email-18.0.1.0.0.2.dist-info/top_level.txt
odoo_addon_sale_order_cancel_optional_email-18.0.1.0.0.2.dist-info/RECORD
